django_vite_plugin/__init__.py
django_vite_plugin/cache.py
django_vite_plugin/config_helper.py
django_vite_plugin/constants.py
django_vite_plugin/html.py
django_vite_plugin/manifest.py
django_vite_plugin/urls.py
django_vite_plugin/utils.py
django_vite_plugin/management/commands/__init__.py
django_vite_plugin/management/commands/django_vite_plugin.py
django_vite_plugin/management/commands/utils.py
django_vite_plugin/templatetags/__init__.py
django_vite_plugin/templatetags/nodes.py
django_vite_plugin/templatetags/utils.py
django_vite_plugin/templatetags/vite.py
django_vite_plugin-4.1.2.dist-info/METADATA
django_vite_plugin-4.1.2.dist-info/WHEEL
django_vite_plugin-4.1.2.dist-info/licenses/LICENSE
django_vite_plugin-4.1.2.dist-info/RECORD
