Metadata-Version: 2.4
Name: django_vite_plugin
Version: 4.1.2
Summary: Vite build tools integration for django
Project-URL: Homepage, https://github.com/protibimbok/django-vite-plugin
Project-URL: Bug Tracker, https://github.com/protibimbok/django-vite-plugin/issues
Author-email: Sakibur Rahman Khan <sakib.saad.khan@gmail.com>
License-File: LICENSE
Classifier: License :: OSI Approved :: MIT License
Classifier: Operating System :: OS Independent
Classifier: Programming Language :: Python :: 3
Requires-Python: >=3.7
